bkregression/__init__.py
bkregression/kernel_smoothing.py
bkregression/kernels.py
bkregression-0.0.2.dist-info/LICENSE
bkregression-0.0.2.dist-info/METADATA
bkregression-0.0.2.dist-info/WHEEL
bkregression-0.0.2.dist-info/top_level.txt
bkregression-0.0.2.dist-info/RECORD
